azcore/__init__.py
azcore/exceptions.py
azcore/agents/__init__.py
azcore/agents/agent_factory.py
azcore/agents/agent_judge.py
azcore/agents/agent_pattern_router.py
azcore/agents/agent_registry.py
azcore/agents/agent_router.py
azcore/agents/enhanced_agent.py
azcore/agents/mcp_team_builder.py
azcore/agents/react_agent.py
azcore/agents/reasoning_duo_agent.py
azcore/agents/reflexion_agent.py
azcore/agents/self_consistency_agent.py
azcore/agents/team_builder.py
azcore/backends/__init__.py
azcore/backends/composite.py
azcore/backends/filesystem.py
azcore/backends/protocol.py
azcore/backends/state.py
azcore/backends/store.py
azcore/backends/utils.py
azcore/cli/__init__.py
azcore/cli/__main__.py
azcore/cli/error_handler.py
azcore/cli/main.py
azcore/cli/scaffolding.py
azcore/cli/commands/__init__.py
azcore/cli/commands/agent.py
azcore/cli/commands/create.py
azcore/cli/commands/doctor.py
azcore/cli/commands/examples.py
azcore/cli/commands/init.py
azcore/cli/commands/run.py
azcore/cli/commands/stats.py
azcore/cli/commands/train.py
azcore/cli/commands/upgrade.py
azcore/cli/commands/validate.py
azcore/cli/templates/__init__.py
azcore/cli/templates/agent_templates.py
azcore/cli/templates/config_templates.py
azcore/cli/templates/misc_templates.py
azcore/cli/templates/workflow_templates.py
azcore/cli/templates/team_modules/__init__.py
azcore/cli/templates/team_modules/communication_tools.py
azcore/cli/templates/team_modules/data_tools.py
azcore/cli/templates/team_modules/file_tools.py
azcore/cli/templates/team_modules/graph_builder.py
azcore/cli/templates/team_modules/main_template.py
azcore/cli/templates/team_modules/research_tools.py
azcore/cli/templates/team_modules/utils.py
azcore/config/__init__.py
azcore/config/config.py
azcore/config/settings.py
azcore/config/validation.py
azcore/core/__init__.py
azcore/core/agent_executor.py
azcore/core/base.py
azcore/core/orchestrator.py
azcore/core/state.py
azcore/core/supervisor.py
azcore/middleware/__init__.py
azcore-0.0.11.dist-info/licenses/LICENSE
azcore-0.0.11.dist-info/METADATA
azcore-0.0.11.dist-info/WHEEL
azcore-0.0.11.dist-info/entry_points.txt
azcore-0.0.11.dist-info/top_level.txt
azcore-0.0.11.dist-info/RECORD
