Metadata-Version: 2.4
Name: azcore
Version: 0.0.11
Summary: A professional hierarchical multi-agent framework built on python.
Home-page: https://github.com/Azrienlabs/Az-Core
Author: Azrienlabs team
Author-email: info@azrianlabs.com
License: MIT
Project-URL: Bug Reports, https://github.com/Azrienlabs/Az-Core/issues
Project-URL: Source, https://github.com/Azrienlabs/Az-Core
Project-URL: Documentation, https://docs.azrienlabs.com/
Keywords: Multi-agent agents ai framework hierarchical azcore reinforcement-learning
Classifier: Development Status :: 4 - Beta
Classifier: Intended Audience :: Developers
Classifier: Topic :: Software Development :: Libraries :: Application Frameworks
Classifier: Topic :: Scientific/Engineering :: Artificial Intelligence
Classifier: License :: OSI Approved :: MIT License
Classifier: Programming Language :: Python :: 3.12
Requires-Python: >=3.12
License-File: LICENSE
Requires-Dist: annotated-types>=0.7.0
Requires-Dist: anyio>=4.12.0
Requires-Dist: attrs>=25.4.0
Requires-Dist: certifi>=2025.11.12
Requires-Dist: cffi>=2.0.0
Requires-Dist: charset-normalizer>=3.4.4
Requires-Dist: click>=8.3.1
Requires-Dist: colorama>=0.4.6
Requires-Dist: cryptography>=46.0.3
Requires-Dist: distro>=1.9.0
Requires-Dist: dotenv>=0.9.9
Requires-Dist: filelock>=3.20.0
Requires-Dist: fsspec>=2025.12.0
Requires-Dist: h11>=0.16.0
Requires-Dist: httpcore>=1.0.9
Requires-Dist: httpx>=0.28.1
Requires-Dist: httpx-sse>=0.4.3
Requires-Dist: huggingface-hub>=0.36.0
Requires-Dist: idna>=3.11
Requires-Dist: Jinja2>=3.1.6
Requires-Dist: jiter>=0.12.0
Requires-Dist: joblib>=1.5.2
Requires-Dist: jsonpatch>=1.33
Requires-Dist: jsonpointer>=3.0.0
Requires-Dist: jsonschema>=4.25.1
Requires-Dist: jsonschema-specifications>=2025.9.1
Requires-Dist: langchain>=1.1.3
Requires-Dist: langchain-core>=1.1.2
Requires-Dist: langchain-mcp-adapters>=0.1.14
Requires-Dist: langchain-openai>=1.1.1
Requires-Dist: langgraph>=1.0.4
Requires-Dist: langgraph-checkpoint>=3.0.1
Requires-Dist: langgraph-prebuilt>=1.0.5
Requires-Dist: langgraph-sdk>=0.2.14
Requires-Dist: langsmith>=0.4.56
Requires-Dist: MarkupSafe>=3.0.3
Requires-Dist: mcp>=1.23.2
Requires-Dist: mpmath>=1.3.0
Requires-Dist: networkx>=3.6.1
Requires-Dist: numpy>=2.3.5
Requires-Dist: openai>=2.9.0
Requires-Dist: orjson>=3.11.5
Requires-Dist: ormsgpack>=1.12.0
Requires-Dist: packaging>=25.0
Requires-Dist: pillow>=12.0.0
Requires-Dist: pycparser>=2.23
Requires-Dist: pydantic>=2.12.5
Requires-Dist: pydantic-settings>=2.12.0
Requires-Dist: pydantic_core>=2.41.5
Requires-Dist: PyJWT>=2.10.1
Requires-Dist: python-dotenv>=1.2.1
Requires-Dist: python-multipart>=0.0.20
Requires-Dist: pywin32>=311
Requires-Dist: PyYAML>=6.0.3
Requires-Dist: referencing>=0.37.0
Requires-Dist: regex>=2025.11.3
Requires-Dist: requests>=2.32.5
Requires-Dist: requests-toolbelt>=1.0.0
Requires-Dist: rpds-py>=0.30.0
Requires-Dist: safetensors>=0.7.0
Requires-Dist: scikit-learn>=1.7.2
Requires-Dist: scipy>=1.16.3
Requires-Dist: sentence-transformers>=5.1.2
Requires-Dist: sniffio>=1.3.1
Requires-Dist: sse-starlette>=3.0.3
Requires-Dist: starlette>=0.50.0
Requires-Dist: sympy>=1.14.0
Requires-Dist: tenacity>=9.1.2
Requires-Dist: threadpoolctl>=3.6.0
Requires-Dist: tiktoken>=0.12.0
Requires-Dist: tokenizers>=0.22.1
Requires-Dist: torch>=2.9.1
Requires-Dist: tqdm>=4.67.1
Requires-Dist: transformers>=4.57.3
Requires-Dist: typing-inspection>=0.4.2
Requires-Dist: typing_extensions>=4.15.0
Requires-Dist: urllib3>=2.6.1
Requires-Dist: uvicorn>=0.38.0
Requires-Dist: xxhash>=3.6.0
Requires-Dist: zstandard>=0.25.0
Provides-Extra: dev
Requires-Dist: pytest>=7.0.0; extra == "dev"
Requires-Dist: pytest-cov>=4.0.0; extra == "dev"
Requires-Dist: pytest-asyncio>=0.21.0; extra == "dev"
Requires-Dist: black>=23.0.0; extra == "dev"
Requires-Dist: flake8>=6.0.0; extra == "dev"
Requires-Dist: mypy>=1.0.0; extra == "dev"
Provides-Extra: mcp
Requires-Dist: langchain-mcp-adapters>=0.1.0; extra == "mcp"
Provides-Extra: rl
Requires-Dist: torch>=2.0.0; extra == "rl"
Requires-Dist: sentence-transformers>=2.0.0; extra == "rl"
Requires-Dist: scikit-learn>=1.0.0; extra == "rl"
Dynamic: author
Dynamic: author-email
Dynamic: classifier
Dynamic: description
Dynamic: description-content-type
Dynamic: home-page
Dynamic: keywords
Dynamic: license
Dynamic: license-file
Dynamic: project-url
Dynamic: provides-extra
Dynamic: requires-dist
Dynamic: requires-python
Dynamic: summary
